chipfiring/CFCombinatorics.py
chipfiring/CFConfig.py
chipfiring/CFDataProcessor.py
chipfiring/CFDhar.py
chipfiring/CFDivisor.py
chipfiring/CFEWDVisualizer.py
chipfiring/CFGonality.py
chipfiring/CFGonalityDhar.py
chipfiring/CFGraph.py
chipfiring/CFGreedyAlgorithm.py
chipfiring/CFLaplacian.py
chipfiring/CFOrientation.py
chipfiring/CFPlatonicSolids.py
chipfiring/CFRank.py
chipfiring/CFVisualizer.py
chipfiring/CFiringScript.py
chipfiring/__init__.py
chipfiring/algo.py
chipfiring-1.1.3.dist-info/licenses/LICENSE.txt
docs/__init__.py
docs/conf.py
tests/__init__.py
tests/conftest.py
tests/test_CFEWDVisualizer.py
tests/test_algo.py
tests/test_cfcombinatorics.py
tests/test_cfconfig.py
tests/test_cfdataprocessor.py
tests/test_cfdhar.py
tests/test_cfdivisor.py
tests/test_cfgonality.py
tests/test_cfgraph.py
tests/test_cfgreedyalgorithm.py
tests/test_cfiringscript.py
tests/test_cflaplacian.py
tests/test_cforientation.py
tests/test_cfrank.py
tests/test_cfvisualizer.py
chipfiring-1.1.3.dist-info/METADATA
chipfiring-1.1.3.dist-info/WHEEL
chipfiring-1.1.3.dist-info/top_level.txt
chipfiring-1.1.3.dist-info/RECORD
