Metadata-Version: 2.4
Name: chipfiring
Version: 1.1.3
Summary: This is an Pythonic API for visualization and analysis of chip firing games and corresponding algorithms.
Home-page: https://github.com/DhyeyMavani2003/chipfiring
Author: Dhyey Mavani
License: MIT
Classifier: Programming Language :: Python
License-File: LICENSE.txt
Requires-Dist: numpy
Requires-Dist: pandas
Requires-Dist: pytest
Requires-Dist: coverage
Requires-Dist: matplotlib
Requires-Dist: dash
Requires-Dist: dash-cytoscape
Requires-Dist: dash-bootstrap-components
Requires-Dist: networkx
Dynamic: author
Dynamic: classifier
Dynamic: description
Dynamic: description-content-type
Dynamic: home-page
Dynamic: keywords
Dynamic: license
Dynamic: license-file
Dynamic: requires-dist
Dynamic: summary
